rosemary/__init__.py
rosemary/alembic/README
rosemary/alembic/__init__.py
rosemary/alembic/env.py
rosemary/alembic/script.py.mako
rosemary/alembic/versions/25ed0f563bdc_add_delay.py
rosemary/alembic/versions/9bb6f1128279_update_key_to_worker.py
rosemary/alembic/versions/__init__.py
rosemary/alembic/versions/ddebc53e7879_init.py
rosemary/core/__init__.py
rosemary/core/custom_semaphore.py
rosemary/core/logger.py
rosemary/db/__init__.py
rosemary/db/alembic.py
rosemary/db/db.py
rosemary/db/models.py
rosemary/interval.py
rosemary/rosemary.py
rosemary/settings.py
rosemary/tasks/__init__.py
rosemary/tasks/constants.py
rosemary/tasks/manual_task.py
rosemary/tasks/repeatable_task.py
rosemary/tasks/task_interface.py
rosemary/worker/__init__.py
rosemary/worker/constants.py
rosemary/worker/exception.py
rosemary/worker/main_worker.py
rosemary/worker/worker.py
rosemary/worker/worker_interface.py
rosemary-1.8.0.dist-info/LICENSE
rosemary-1.8.0.dist-info/METADATA
rosemary-1.8.0.dist-info/WHEEL
rosemary-1.8.0.dist-info/RECORD
