Metadata-Version: 2.1
Name: rosemary
Version: 1.8.0
Summary: 
Author: Chris Odi
Author-email: chris.odi76@gmail.com
Requires-Python: >=3.11,<4.0
Classifier: Programming Language :: Python :: 3
Classifier: Programming Language :: Python :: 3.11
Requires-Dist: alembic (>=1,<2)
Requires-Dist: asyncio (>=3,<4)
Requires-Dist: asyncpg (>=0.29.0,<0.30.0)
Requires-Dist: greenlet (>=3,<4)
Requires-Dist: importlib (>=1,<2)
Requires-Dist: logger (>=1,<2)
Requires-Dist: pydantic (>=2,<3)
Requires-Dist: setuptools (>=69,<70)
Requires-Dist: sqlalchemy (>=2,<3)
